stocktonesportsbot
stocktonesportsbot/classes
