Metadata-Version: 2.1
Name: stocktonesportsbot
Version: 1.2
Summary: A Discord bot for Stockton University's Esports Discord Server
Home-page: https://github.com/Dual-Exhaust/Stockton-Esports-Bot
Author: Dual-Exhaust
Author-email: kylecsacco@gmail.com
License: MIT
Platform: UNKNOWN
Requires-Python: >=3.7
